Workbook

Sheet Tổng quan
A1: Folio (Doc Reader & Creator) — Báo cáo test chức năng
A3: Ngày test | B3: 26/10/2026
A4: Bản build | B4: devDebug 1.0.0 (6), nhánh reskin-v2 @ e18b8d1
A5: Thiết bị | B5: Samsung Galaxy A16 (SM-A165F), Android 16, 1080×2340
A6: Phương pháp | B6: Test thủ công theo luồng end-user qua adb (uiautomator + ảnh chụp) và monkey stress
A7: Dữ liệu test | B7: store-assets/samples + QA_form.pdf, QA_scanned.pdf, QA_corrupt.pdf, QA_empty.pdf, file có mật khẩu, 3 ảnh JPG (thư mục Download/QA)
A9: Kết quả theo trạng thái
B10: Tổng | C10: Pass | D10: Fail | E10: Not run | F10: % Pass (đã chạy)
A11: Tất cả | B11: =COUNTA('Test Cases'!A2:A266) | C11: =COUNTIF('Test Cases'!J2:J266,"Pass") | D11: =COUNTIF('Test Cases'!J2:J266,"Fail") | E11: =COUNTIF('Test Cases'!J2:J266,"Not run") | F11: =IFERROR(C11/(C11+D11),0)
A13: Kết quả theo module
A14: Module | B14: Tổng | C14: Pass | D14: Fail | E14: Not run | F14: % Pass (đã chạy)
A15: First-run | B15: =COUNTIF('Test Cases'!B2:B266,A15) | C15: =COUNTIFS('Test Cases'!B2:B266,A15,'Test Cases'!J2:J266,"Pass") | D15: =COUNTIFS('Test Cases'!B2:B266,A15,'Test Cases'!J2:J266,"Fail") | E15: =COUNTIFS('Test Cases'!B2:B266,A15,'Test Cases'!J2:J266,"Not run") | F15: =IFERROR(C15/(C15+D15),0)
A16: Màn chính - Files | B16: =COUNTIF('Test Cases'!B2:B266,A16) | C16: =COUNTIFS('Test Cases'!B2:B266,A16,'Test Cases'!J2:J266,"Pass") | D16: =COUNTIFS('Test Cases'!B2:B266,A16,'Test Cases'!J2:J266,"Fail") | E16: =COUNTIFS('Test Cases'!B2:B266,A16,'Test Cases'!J2:J266,"Not run") | F16: =IFERROR(C16/(C16+D16),0)
A17: All files | B17: =COUNTIF('Test Cases'!B2:B266,A17) | C17: =COUNTIFS('Test Cases'!B2:B266,A17,'Test Cases'!J2:J266,"Pass") | D17: =COUNTIFS('Test Cases'!B2:B266,A17,'Test Cases'!J2:J266,"Fail") | E17: =COUNTIFS('Test Cases'!B2:B266,A17,'Test Cases'!J2:J266,"Not run") | F17: =IFERROR(C17/(C17+D17),0)
A18: Tìm kiếm | B18: =COUNTIF('Test Cases'!B2:B266,A18) | C18: =COUNTIFS('Test Cases'!B2:B266,A18,'Test Cases'!J2:J266,"Pass") | D18: =COUNTIFS('Test Cases'!B2:B266,A18,'Test Cases'!J2:J266,"Fail") | E18: =COUNTIFS('Test Cases'!B2:B266,A18,'Test Cases'!J2:J266,"Not run") | F18: =IFERROR(C18/(C18+D18),0)
A19: Tab Tools | B19: =COUNTIF('Test Cases'!B2:B266,A19) | C19: =COUNTIFS('Test Cases'!B2:B266,A19,'Test Cases'!J2:J266,"Pass") | D19: =COUNTIFS('Test Cases'!B2:B266,A19,'Test Cases'!J2:J266,"Fail") | E19: =COUNTIFS('Test Cases'!B2:B266,A19,'Test Cases'!J2:J266,"Not run") | F19: =IFERROR(C19/(C19+D19),0)
A20: Chọn file (Step 1) | B20: =COUNTIF('Test Cases'!B2:B266,A20) | C20: =COUNTIFS('Test Cases'!B2:B266,A20,'Test Cases'!J2:J266,"Pass") | D20: =COUNTIFS('Test Cases'!B2:B266,A20,'Test Cases'!J2:J266,"Fail") | E20: =COUNTIFS('Test Cases'!B2:B266,A20,'Test Cases'!J2:J266,"Not run") | F20: =IFERROR(C20/(C20+D20),0)
A21: Merge PDF | B21: =COUNTIF('Test Cases'!B2:B266,A21) | C21: =COUNTIFS('Test Cases'!B2:B266,A21,'Test Cases'!J2:J266,"Pass") | D21: =COUNTIFS('Test Cases'!B2:B266,A21,'Test Cases'!J2:J266,"Fail") | E21: =COUNTIFS('Test Cases'!B2:B266,A21,'Test Cases'!J2:J266,"Not run") | F21: =IFERROR(C21/(C21+D21),0)
A22: Split PDF | B22: =COUNTIF('Test Cases'!B2:B266,A22) | C22: =COUNTIFS('Test Cases'!B2:B266,A22,'Test Cases'!J2:J266,"Pass") | D22: =COUNTIFS('Test Cases'!B2:B266,A22,'Test Cases'!J2:J266,"Fail") | E22: =COUNTIFS('Test Cases'!B2:B266,A22,'Test Cases'!J2:J266,"Not run") | F22: =IFERROR(C22/(C22+D22),0)
A23: Compress | B23: =COUNTIF('Test Cases'!B2:B266,A23) | C23: =COUNTIFS('Test Cases'!B2:B266,A23,'Test Cases'!J2:J266,"Pass") | D23: =COUNTIFS('Test Cases'!B2:B266,A23,'Test Cases'!J2:J266,"Fail") | E23: =COUNTIFS('Test Cases'!B2:B266,A23,'Test Cases'!J2:J266,"Not run") | F23: =IFERROR(C23/(C23+D23),0)
A24: Protect | B24: =COUNTIF('Test Cases'!B2:B266,A24) | C24: =COUNTIFS('Test Cases'!B2:B266,A24,'Test Cases'!J2:J266,"Pass") | D24: =COUNTIFS('Test Cases'!B2:B266,A24,'Test Cases'!J2:J266,"Fail") | E24: =COUNTIFS('Test Cases'!B2:B266,A24,'Test Cases'!J2:J266,"Not run") | F24: =IFERROR(C24/(C24+D24),0)
A25: Watermark | B25: =COUNTIF('Test Cases'!B2:B266,A25) | C25: =COUNTIFS('Test Cases'!B2:B266,A25,'Test Cases'!J2:J266,"Pass") | D25: =COUNTIFS('Test Cases'!B2:B266,A25,'Test Cases'!J2:J266,"Fail") | E25: =COUNTIFS('Test Cases'!B2:B266,A25,'Test Cases'!J2:J266,"Not run") | F25: =IFERROR(C25/(C25+D25),0)
A26: Redact | B26: =COUNTIF('Test Cases'!B2:B266,A26) | C26: =COUNTIFS('Test Cases'!B2:B266,A26,'Test Cases'!J2:J266,"Pass") | D26: =COUNTIFS('Test Cases'!B2:B266,A26,'Test Cases'!J2:J266,"Fail") | E26: =COUNTIFS('Test Cases'!B2:B266,A26,'Test Cases'!J2:J266,"Not run") | F26: =IFERROR(C26/(C26+D26),0)
A27: OCR | B27: =COUNTIF('Test Cases'!B2:B266,A27) | C27: =COUNTIFS('Test Cases'!B2:B266,A27,'Test Cases'!J2:J266,"Pass") | D27: =COUNTIFS('Test Cases'!B2:B266,A27,'Test Cases'!J2:J266,"Fail") | E27: =COUNTIFS('Test Cases'!B2:B266,A27,'Test Cases'!J2:J266,"Not run") | F27: =IFERROR(C27/(C27+D27),0)
A28: Translate | B28: =COUNTIF('Test Cases'!B2:B266,A28) | C28: =COUNTIFS('Test Cases'!B2:B266,A28,'Test Cases'!J2:J266,"Pass") | D28: =COUNTIFS('Test Cases'!B2:B266,A28,'Test Cases'!J2:J266,"Fail") | E28: =COUNTIFS('Test Cases'!B2:B266,A28,'Test Cases'!J2:J266,"Not run") | F28: =IFERROR(C28/(C28+D28),0)
A29: ZIP | B29: =COUNTIF('Test Cases'!B2:B266,A29) | C29: =COUNTIFS('Test Cases'!B2:B266,A29,'Test Cases'!J2:J266,"Pass") | D29: =COUNTIFS('Test Cases'!B2:B266,A29,'Test Cases'!J2:J266,"Fail") | E29: =COUNTIFS('Test Cases'!B2:B266,A29,'Test Cases'!J2:J266,"Not run") | F29: =IFERROR(C29/(C29+D29),0)
A30: Photos to PDF | B30: =COUNTIF('Test Cases'!B2:B266,A30) | C30: =COUNTIFS('Test Cases'!B2:B266,A30,'Test Cases'!J2:J266,"Pass") | D30: =COUNTIFS('Test Cases'!B2:B266,A30,'Test Cases'!J2:J266,"Fail") | E30: =COUNTIFS('Test Cases'!B2:B266,A30,'Test Cases'!J2:J266,"Not run") | F30: =IFERROR(C30/(C30+D30),0)
A31: PDF to images | B31: =COUNTIF('Test Cases'!B2:B266,A31) | C31: =COUNTIFS('Test Cases'!B2:B266,A31,'Test Cases'!J2:J266,"Pass") | D31: =COUNTIFS('Test Cases'!B2:B266,A31,'Test Cases'!J2:J266,"Fail") | E31: =COUNTIFS('Test Cases'!B2:B266,A31,'Test Cases'!J2:J266,"Not run") | F31: =IFERROR(C31/(C31+D31),0)
A32: Office to PDF | B32: =COUNTIF('Test Cases'!B2:B266,A32) | C32: =COUNTIFS('Test Cases'!B2:B266,A32,'Test Cases'!J2:J266,"Pass") | D32: =COUNTIFS('Test Cases'!B2:B266,A32,'Test Cases'!J2:J266,"Fail") | E32: =COUNTIFS('Test Cases'!B2:B266,A32,'Test Cases'!J2:J266,"Not run") | F32: =IFERROR(C32/(C32+D32),0)
A33: Processing & Success | B33: =COUNTIF('Test Cases'!B2:B266,A33) | C33: =COUNTIFS('Test Cases'!B2:B266,A33,'Test Cases'!J2:J266,"Pass") | D33: =COUNTIFS('Test Cases'!B2:B266,A33,'Test Cases'!J2:J266,"Fail") | E33: =COUNTIFS('Test Cases'!B2:B266,A33,'Test Cases'!J2:J266,"Not run") | F33: =IFERROR(C33/(C33+D33),0)
A34: PDF Reader | B34: =COUNTIF('Test Cases'!B2:B266,A34) | C34: =COUNTIFS('Test Cases'!B2:B266,A34,'Test Cases'!J2:J266,"Pass") | D34: =COUNTIFS('Test Cases'!B2:B266,A34,'Test Cases'!J2:J266,"Fail") | E34: =COUNTIFS('Test Cases'!B2:B266,A34,'Test Cases'!J2:J266,"Not run") | F34: =IFERROR(C34/(C34+D34),0)
A35: Office - Word | B35: =COUNTIF('Test Cases'!B2:B266,A35) | C35: =COUNTIFS('Test Cases'!B2:B266,A35,'Test Cases'!J2:J266,"Pass") | D35: =COUNTIFS('Test Cases'!B2:B266,A35,'Test Cases'!J2:J266,"Fail") | E35: =COUNTIFS('Test Cases'!B2:B266,A35,'Test Cases'!J2:J266,"Not run") | F35: =IFERROR(C35/(C35+D35),0)
A36: Office - Excel | B36: =COUNTIF('Test Cases'!B2:B266,A36) | C36: =COUNTIFS('Test Cases'!B2:B266,A36,'Test Cases'!J2:J266,"Pass") | D36: =COUNTIFS('Test Cases'!B2:B266,A36,'Test Cases'!J2:J266,"Fail") | E36: =COUNTIFS('Test Cases'!B2:B266,A36,'Test Cases'!J2:J266,"Not run") | F36: =IFERROR(C36/(C36+D36),0)
A37: Office - PowerPoint | B37: =COUNTIF('Test Cases'!B2:B266,A37) | C37: =COUNTIFS('Test Cases'!B2:B266,A37,'Test Cases'!J2:J266,"Pass") | D37: =COUNTIFS('Test Cases'!B2:B266,A37,'Test Cases'!J2:J266,"Fail") | E37: =COUNTIFS('Test Cases'!B2:B266,A37,'Test Cases'!J2:J266,"Not run") | F37: =IFERROR(C37/(C37+D37),0)
A38: Scanner | B38: =COUNTIF('Test Cases'!B2:B266,A38) | C38: =COUNTIFS('Test Cases'!B2:B266,A38,'Test Cases'!J2:J266,"Pass") | D38: =COUNTIFS('Test Cases'!B2:B266,A38,'Test Cases'!J2:J266,"Fail") | E38: =COUNTIFS('Test Cases'!B2:B266,A38,'Test Cases'!J2:J266,"Not run") | F38: =IFERROR(C38/(C38+D38),0)
A39: Settings | B39: =COUNTIF('Test Cases'!B2:B266,A39) | C39: =COUNTIFS('Test Cases'!B2:B266,A39,'Test Cases'!J2:J266,"Pass") | D39: =COUNTIFS('Test Cases'!B2:B266,A39,'Test Cases'!J2:J266,"Fail") | E39: =COUNTIFS('Test Cases'!B2:B266,A39,'Test Cases'!J2:J266,"Not run") | F39: =IFERROR(C39/(C39+D39),0)
A40: Mạng | B40: =COUNTIF('Test Cases'!B2:B266,A40) | C40: =COUNTIFS('Test Cases'!B2:B266,A40,'Test Cases'!J2:J266,"Pass") | D40: =COUNTIFS('Test Cases'!B2:B266,A40,'Test Cases'!J2:J266,"Fail") | E40: =COUNTIFS('Test Cases'!B2:B266,A40,'Test Cases'!J2:J266,"Not run") | F40: =IFERROR(C40/(C40+D40),0)
A41: Accessibility | B41: =COUNTIF('Test Cases'!B2:B266,A41) | C41: =COUNTIFS('Test Cases'!B2:B266,A41,'Test Cases'!J2:J266,"Pass") | D41: =COUNTIFS('Test Cases'!B2:B266,A41,'Test Cases'!J2:J266,"Fail") | E41: =COUNTIFS('Test Cases'!B2:B266,A41,'Test Cases'!J2:J266,"Not run") | F41: =IFERROR(C41/(C41+D41),0)
A42: Crash & Stress | B42: =COUNTIF('Test Cases'!B2:B266,A42) | C42: =COUNTIFS('Test Cases'!B2:B266,A42,'Test Cases'!J2:J266,"Pass") | D42: =COUNTIFS('Test Cases'!B2:B266,A42,'Test Cases'!J2:J266,"Fail") | E42: =COUNTIFS('Test Cases'!B2:B266,A42,'Test Cases'!J2:J266,"Not run") | F42: =IFERROR(C42/(C42+D42),0)
A44: Bug theo mức độ
A45: Mức độ | B45: Số bug
A46: High | B46: =COUNTIF(Bugs!C2:C16,A46)
A47: Medium | B47: =COUNTIF(Bugs!C2:C16,A47)
A48: Low | B48: =COUNTIF(Bugs!C2:C16,A48)
A49: Crash / ANR (monkey ~22.000 sự kiện) | B49: ='Crash & Stress'!E8+'Crash & Stress'!F8
A52: Cách dùng
A53: Sheet 'Test Cases': cột 'Trạng thái' chọn Pass / Fail / Not run / Blocked; các bảng ở sheet này tự tính lại.
A54: 'Not run' = chưa chạy được trên máy lần này (first-run cần xoá dữ liệu app, cần giấy thật cho auto-scan, máy bị khoá PIN khi test thu hồi quyền, cần tắt mạng…).
A55: Cột 'Bug' trỏ sang sheet 'Bugs'; ảnh chụp nằm trong thư mục screenshots/ cạnh file này.

Sheet Test Cases
A1: ID | B1: Module | C1: Chức năng | D1: Test case | E1: Tiền điều kiện | F1: Các bước | G1: Dữ liệu test | H1: Kết quả mong đợi | I1: Kết quả thực tế | J1: Trạng thái | K1: Ưu tiên | L1: Loại | M1: Bug
A2: FR-001 | B2: First-run | C2: Splash | D2: Mở app lần đầu hiển thị Splash rồi sang chọn ngôn ngữ | E2: Cài mới / xoá dữ liệu app | F2: 1. Mở app từ launcher | H2: Splash hiển thị, sau đó chuyển LanguageActivity | J2: Not run | K2: High | L2: Functional
A3: FR-002 | B3: First-run | C3: Language | D3: Chọn ngôn ngữ và Continue | E3: Đang ở màn chọn ngôn ngữ | F3: 1. Chọn Tiếng Việt 2. Bấm Continue | G3: Tiếng Việt | H3: Chuyển sang Onboarding, toàn bộ chữ hiển thị tiếng Việt | J3: Not run | K3: High | L3: Functional
A4: FR-003 | B4: First-run | C4: Onboarding | D4: Vuốt qua các trang onboarding | E4: Đang ở Onboarding | F4: 1. Vuốt/bấm Next qua từng trang 2. Bấm Start ở trang cuối | H4: Indicator đổi theo trang, trang cuối sang Welcome | J4: Not run | K4: Medium | L4: Functional
A5: FR-004 | B5: First-run | C5: Welcome | D5: Chọn mục đích sử dụng (nhiều lựa chọn) | E5: Đang ở Welcome | F5: 1. Chọn Work + Study 2. Bấm Continue | H5: Đếm 'n picked' đúng, sang màn cấp quyền | J5: Not run | K5: Medium | L5: Functional
A6: FR-005 | B6: First-run | C6: Permission | D6: Cấp quyền All files access | E6: Đang ở PermissionActivity | F6: 1. Bấm Allow access 2. Bật quyền trong Settings hệ thống 3. Quay lại app | H6: App tự nhận quyền, chuyển IntroPaywall (nếu bật) hoặc MainActivity | J6: Not run | K6: High | L6: Functional
A7: FR-006 | B7: First-run | C7: Permission | D7: Từ chối quyền bộ nhớ | E7: Đang ở PermissionActivity | F7: 1. Bấm Allow access 2. Không bật quyền, quay lại | H7: App vẫn vào được Main, tab Files hiện 'Your library' + Allow access / Open a file | J7: Not run | K7: High | L7: Negative
A8: FR-007 | B8: First-run | C8: Splash | D8: Mở app lần sau bỏ qua first-run | E8: App đã cài, đã qua first-run, đã cấp quyền bộ nhớ | F8: 1. Force stop 2. Mở lại app | H8: Splash → MainActivity, không hiện lại Language/Onboarding | I8: Splash → MainActivity, tab Files | J8: Pass | K8: High | L8: Functional
A9: HOME-001 | B9: Màn chính - Files | C9: Bottom bar | D9: Chuyển tab Files / Tools / Settings | E9: App đã cài, đã qua first-run, đã cấp quyền bộ nhớ | F9: 1. Bấm Tools 2. Bấm Settings 3. Bấm Files | H9: Mỗi tab hiển thị đúng, tab đang chọn được tô sáng | I9: Đúng | J9: Pass | K9: High | L9: Functional
A10: HOME-002 | B10: Màn chính - Files | C10: Header | D10: Lời chào theo giờ + số file | E10: App đã cài, đã qua first-run, đã cấp quyền bộ nhớ | F10: 1. Mở tab Files | H10: Hiện 'Good evening/morning…' và 'N files on this phone' | I10: Hiện 'Good evening', '336 files on this phone' | J10: Pass | K10: Low | L10: Functional
A11: HOME-003 | B11: Màn chính - Files | C11: Read card | D11: Bấm card Read | E11: App đã cài, đã qua first-run, đã cấp quyền bộ nhớ | F11: 1. Bấm card Read | H11: Mở All files | I11: Mở AllFilesActivity | J11: Pass | K11: High | L11: Functional
A12: HOME-004 | B12: Màn chính - Files | C12: Create card | D12: Bấm card Create | E12: App đã cài, đã qua first-run, đã cấp quyền bộ nhớ | F12: 1. Bấm card Create | H12: Mở bottom sheet 'What shall we make?' | I12: Sheet hiện Scan / Photos to PDF / Word / Excel / PowerPoint / Not now | J12: Pass | K12: High | L12: Functional
A13: HOME-005 | B13: Màn chính - Files | C13: Your documents | D13: Bấm ô PDF trong 'Your documents' | E13: App đã cài, đã qua first-run, đã cấp quyền bộ nhớ | F13: 1. Bấm ô PDF | H13: All files mở tab All, chip PDF được chọn, chỉ có file PDF | I13: Đúng | J13: Pass | K13: High | L13: Functional
A14: HOME-006 | B14: Màn chính - Files | C14: Your documents | D14: Bấm ô PPT | E14: App đã cài, đã qua first-run, đã cấp quyền bộ nhớ | F14: 1. Bấm ô PPT | H14: All files lọc PowerPoint | I14: Đúng | J14: Pass | K14: Medium | L14: Functional
A15: HOME-007 | B15: Màn chính - Files | C15: Your documents | D15: Số đếm file theo loại cập nhật khi thêm file | E15: App đã cài, đã qua first-run, đã cấp quyền bộ nhớ | F15: 1. Push thêm file PDF/DOCX/XLSX/PPTX 2. Quay lại tab Files | G15: 4 file mẫu | H15: Số đếm tăng tương ứng | I15: PDF 133→134, DOC 84→85… cập nhật đúng | J15: Pass | K15: Medium | L15: Functional
A16: HOME-008 | B16: Màn chính - Files | C16: Start something new | D16: Tạo Word trống | E16: App đã cài, đã qua first-run, đã cấp quyền bộ nhớ | F16: 1. Bấm Document (Word) | H16: Tạo 'Untitled-<Mon-dd>.docx' trong Download/Folio, mở Office ở chế độ Edit, trạng thái Saved | I16: Đúng (Untitled-Oct-26.docx) | J16: Pass | K16: High | L16: Functional
A17: HOME-009 | B17: Màn chính - Files | C17: Start something new | D17: Tạo Excel trống | E17: App đã cài, đã qua first-run, đã cấp quyền bộ nhớ | F17: 1. Bấm Sheet (Excel) | H17: Tạo Untitled .xlsx, mở Edit | I17: Đúng | J17: Pass | K17: High | L17: Functional
A18: HOME-010 | B18: Màn chính - Files | C18: Start something new | D18: Tạo PowerPoint trống | E18: App đã cài, đã qua first-run, đã cấp quyền bộ nhớ | F18: 1. Bấm Slides | H18: Tạo Untitled .pptx, mở Edit có slide strip | I18: Đúng | J18: Pass | K18: High | L18: Functional
A19: HOME-011 | B19: Màn chính - Files | C19: Start something new | D19: Tạo file trùng tên trong cùng ngày | E19: Đã có Untitled-Oct-26.docx | F19: 1. Bấm Document lần 2 | H19: Tên mới không ghi đè (vd Untitled-Oct-26-2.docx) | I19: Đúng (Untitled-Oct-26-2.docx) | J19: Pass | K19: Medium | L19: Edge
A20: HOME-012 | B20: Màn chính - Files | C20: Start something new | D20: Scan to PDF / Photos to PDF từ màn chính | E20: App đã cài, đã qua first-run, đã cấp quyền bộ nhớ | F20: 1. Bấm Scan to PDF 2. Quay lại 3. Bấm Photos to PDF | H20: Mở camera scanner / mở Photo picker | I20: Đúng | J20: Pass | K20: Medium | L20: Functional
A21: HOME-013 | B21: Màn chính - Files | C21: Edit any document | D21: Bấm mũi tên card Edit | E21: App đã cài, đã qua first-run, đã cấp quyền bộ nhớ | F21: 1. Bấm nút > của card Edit any document | H21: Mở danh sách file để chọn | I21: Mở All files | J21: Pass | K21: Medium | L21: Functional
A22: HOME-014 | B22: Màn chính - Files | C22: Edit any document | D22: Chip Add text | E22: App đã cài, đã qua first-run, đã cấp quyền bộ nhớ | F22: 1. Bấm chip Add text 2. Chọn 1 PDF | H22: Mở reader ở chế độ Add text | I22: Đúng | J22: Pass | K22: Medium | L22: Functional
A23: HOME-015 | B23: Màn chính - Files | C23: Edit any document | D23: Chip Sign | E23: App đã cài, đã qua first-run, đã cấp quyền bộ nhớ | F23: 1. Bấm chip Sign 2. Chọn 1 PDF | H23: Mở reader + sheet chữ ký | I23: Đúng | J23: Pass | K23: Medium | L23: Functional
A24: HOME-016 | B24: Màn chính - Files | C24: Edit any document | D24: Chip Annotate / Fill forms / Organize | E24: App đã cài, đã qua first-run, đã cấp quyền bộ nhớ | F24: 1. Bấm từng chip 2. Chọn file | H24: Mở đúng chế độ/màn tương ứng | I24: Annotate, Organize mở picker đúng tiêu đề | J24: Pass | K24: Medium | L24: Functional
A25: HOME-017 | B25: Màn chính - Files | C25: Recent | D25: Danh sách mở gần đây | E25: App đã cài, đã qua first-run, đã cấp quyền bộ nhớ | F25: 1. Mở vài file 2. Quay lại Files, cuộn xuống | H25: File mở gần nhất nằm đầu, tối đa RECENT_LIMIT | J25: Not run | K25: Medium | L25: Functional
A26: HOME-018 | B26: Màn chính - Files | C26: Search | D26: Mở tìm kiếm từ màn chính | E26: App đã cài, đã qua first-run, đã cấp quyền bộ nhớ | F26: 1. Bấm icon kính lúp | H26: Mở SearchActivity, có Recent searches | I26: Đúng | J26: Pass | K26: Medium | L26: Functional
A27: HOME-019 | B27: Màn chính - Files | C27: FAB + | D27: Bấm nút + | E27: App đã cài, đã qua first-run, đã cấp quyền bộ nhớ | F27: 1. Bấm nút + nổi | H27: Mở Create sheet | I27: Đúng | J27: Pass | K27: High | L27: Functional
A28: HOME-020 | B28: Màn chính - Files | C28: Create sheet | D28: Not now đóng sheet | E28: Create sheet đang mở | F28: 1. Bấm Not now | H28: Sheet đóng, không tạo file | J28: Not run | K28: Low | L28: Functional
A29: HOME-021 | B29: Màn chính - Files | C29: Back | D29: Back ở tab khác Files | E29: Đang ở tab Settings | F29: 1. Bấm Back | H29: Quay về tab Files (không thoát app) | I29: Đúng | J29: Pass | K29: Medium | L29: Functional
A30: HOME-022 | B30: Màn chính - Files | C30: Back | D30: Back ở tab Files hiện QuitDialog | E30: Đang ở tab Files | F30: 1. Bấm Back | H30: Hiện 'Heading off already?' với Exit / Stay a bit | I30: Đúng | J30: Pass | K30: Medium | L30: Functional
A31: HOME-023 | B31: Màn chính - Files | C31: Quit dialog | D31: Stay a bit giữ app | E31: QuitDialog đang mở | F31: 1. Bấm Stay a bit | H31: Đóng dialog, ở lại app | J31: Not run | K31: Low | L31: Functional
A32: HOME-024 | B32: Màn chính - Files | C32: Không có quyền | D32: Tab Files khi bị thu hồi quyền | E32: Thu hồi MANAGE_EXTERNAL_STORAGE | F32: 1. Mở app | H32: Hiện 'Your library' + Allow access + Open a file + quick start | I32: Máy bị khoá PIN giữa chừng, chưa chụp được | J32: Not run | K32: High | L32: Negative
A33: HOME-025 | B33: Màn chính - Files | C33: Không có quyền | D33: Open a file qua system picker | E33: Không có quyền bộ nhớ | F33: 1. Bấm Open a file 2. Chọn 1 PDF | H33: Copy về filesDir/opened và mở reader | J33: Not run | K33: High | L33: Functional
A34: ALL-001 | B34: All files | C34: Tabs | D34: Tab Recent | E34: App đã cài, đã qua first-run, đã cấp quyền bộ nhớ | F34: 1. Mở All files 2. Bấm Recent | H34: Liệt kê file đã mở gần đây | I34: Đúng | J34: Pass | K34: Medium | L34: Functional
A35: ALL-002 | B35: All files | C35: Tabs | D35: Tab Favourites rỗng | E35: Chưa có file yêu thích | F35: 1. Bấm Favourites | H35: Empty state 'Nothing here yet' | I35: Đúng | J35: Pass | K35: Low | L35: Edge
A36: ALL-003 | B36: All files | C36: Tabs | D36: Tab All | E36: App đã cài, đã qua first-run, đã cấp quyền bộ nhớ | F36: 1. Bấm All | H36: Liệt kê tất cả tài liệu | I36: Đúng | J36: Pass | K36: Medium | L36: Functional
A37: ALL-004 | B37: All files | C37: Chip loại | D37: Lọc theo PDF / Word / Excel / PowerPoint | E37: App đã cài, đã qua first-run, đã cấp quyền bộ nhớ | F37: 1. Bấm lần lượt từng chip | H37: Chỉ hiện file đúng loại | I37: Đúng | J37: Pass | K37: Medium | L37: Functional
A38: ALL-005 | B38: All files | C38: Sort | D38: Mở sheet sắp xếp | E38: App đã cài, đã qua first-run, đã cấp quyền bộ nhớ | F38: 1. Bấm icon sort | H38: Sheet 'Sort your files': Date / Name / Size / File type + Order | I38: Đúng | J38: Pass | K38: Medium | L38: Functional
A39: ALL-006 | B39: All files | C39: Sort | D39: Sắp xếp theo Name | E39: App đã cài, đã qua first-run, đã cấp quyền bộ nhớ | F39: 1. Sort → Name → Show files | H39: Danh sách theo tên A→Z | I39: F12…, F14…, F15… đúng thứ tự | J39: Pass | K39: Medium | L39: Functional
A40: ALL-007 | B40: All files | C40: Sort | D40: Sắp xếp Date modified Newest first | E40: App đã cài, đã qua first-run, đã cấp quyền bộ nhớ | F40: 1. Sort → Date modified → Newest first → Show files | H40: File mới sửa nằm đầu | I40: QA_ops.pdf (1 min ago) ở đầu | J40: Pass | K40: Medium | L40: Functional
A41: ALL-008 | B41: All files | C41: Sort | D41: Nhãn Order đổi theo tiêu chí | E41: Sheet Sort mở | F41: 1. Chọn Size 2. Chọn Date | H41: Size: Largest/Smallest first; Date: Newest/Oldest first | I41: Đúng | J41: Pass | K41: Low | L41: Functional
A42: ALL-009 | B42: All files | C42: Sort | D42: Sắp xếp theo ngày sau khi sửa file Office | E42: Đã sửa & lưu 1 file pptx/docx | F42: 1. Sort Newest first | H42: File vừa lưu nằm đầu | I42: File vừa lưu vẫn mang ngày cũ (MediaStore date_modified không cập nhật) | J42: Fail | K42: Medium | L42: Functional | M42: BUG-09
A43: ALL-010 | B43: All files | C43: Search | D43: Search từ All files | E43: App đã cài, đã qua first-run, đã cấp quyền bộ nhớ | F43: 1. Bấm kính lúp 2. Gõ 'Project' | G43: Project | H43: Mở Search, ra 3 kết quả tên | I43: Đúng | J43: Pass | K43: Medium | L43: Functional
A44: ALL-011 | B44: All files | C44: File options | D44: Mở sheet tuỳ chọn file (⋮) | E44: App đã cài, đã qua first-run, đã cấp quyền bộ nhớ | F44: 1. Bấm ⋮ trên 1 dòng | H44: Sheet: Share, Favourite, Rename, Copy, File info, Delete | I44: Đúng | J44: Pass | K44: High | L44: Functional
A45: ALL-012 | B45: All files | C45: File options | D45: Thêm vào Favourite | E45: App đã cài, đã qua first-run, đã cấp quyền bộ nhớ | F45: 1. ⋮ → Favourite 2. Mở tab Favourites | H45: File xuất hiện trong Favourites, có icon sao | I45: Đúng | J45: Pass | K45: Medium | L45: Functional
A46: ALL-013 | B46: All files | C46: File options | D46: Bỏ Favourite | E46: File đang là favourite | F46: 1. ⋮ → Favourite lần nữa | H46: File bị gỡ khỏi Favourites | I46: Đúng | J46: Pass | K46: Medium | L46: Functional
A47: ALL-014 | B47: All files | C47: File options | D47: File info | E47: App đã cài, đã qua first-run, đã cấp quyền bộ nhớ | F47: 1. ⋮ → File info | G47: QA_ops.pdf | H47: Hiện Name, Type, Size, Pages, Location, Date modified đúng | I47: Đúng (1 trang, /Download/QA, 2.4 kB) | J47: Pass | K47: Medium | L47: Functional
A48: ALL-015 | B48: All files | C48: Rename | D48: Đổi tên hợp lệ | E48: App đã cài, đã qua first-run, đã cấp quyền bộ nhớ | F48: 1. ⋮ → Rename 2. Nhập 'QA_renamed' 3. Rename | G48: QA_renamed | H48: File đổi tên trên ổ đĩa và trong danh sách, đuôi .pdf giữ nguyên | I48: Đúng | J48: Pass | K48: High | L48: Functional
A49: ALL-016 | B49: All files | C49: Rename | D49: Đổi tên rỗng | E49: Dialog Rename mở | F49: 1. Xoá hết tên 2. Bấm Rename | G49: '' | H49: Không đổi tên, toast báo tên rỗng | I49: Bị chặn, toast | J49: Pass | K49: Medium | L49: Negative
A50: ALL-017 | B50: All files | C50: Rename | D50: Tên chứa ký tự '/' | E50: Dialog Rename mở | F50: 1. Nhập 'a/b' 2. Rename | G50: a/b | H50: Không đổi tên, toast tên không hợp lệ | I50: Bị chặn, toast | J50: Pass | K50: Medium | L50: Negative
A51: ALL-018 | B51: All files | C51: Rename | D51: Đổi sang tên đã tồn tại | E51: Có sẵn 'Rental Agreement.pdf' cùng thư mục | F51: 1. Rename thành 'Rental Agreement' | G51: Rental Agreement | H51: Không ghi đè, báo 'The name may already exist' | I51: Không ghi đè, toast báo lỗi | J51: Pass | K51: High | L51: Negative
A52: ALL-019 | B52: All files | C52: Rename | D52: Tên tiếng Việt có dấu / rất dài | E52: App đã cài, đã qua first-run, đã cấp quyền bộ nhớ | F52: 1. Rename thành tên tiếng Việt 150 ký tự | G52: Tên rất dài có dấu… | H52: Đổi tên thành công hoặc báo lỗi rõ ràng, không crash | J52: Not run | K52: Low | L52: Edge
A53: ALL-020 | B53: All files | C53: Copy | D53: Nhân bản file | E53: App đã cài, đã qua first-run, đã cấp quyền bộ nhớ | F53: 1. ⋮ → Copy | G53: QA_renamed.pdf | H53: Tạo 'QA_renamed (1).pdf' cùng thư mục | I53: Đúng | J53: Pass | K53: Medium | L53: Functional
A54: ALL-021 | B54: All files | C54: Share | D54: Chia sẻ 1 file | E54: App đã cài, đã qua first-run, đã cấp quyền bộ nhớ | F54: 1. ⋮ → Share | H54: Mở share sheet hệ thống với 1 mục | I54: Đúng | J54: Pass | K54: Medium | L54: Functional
A55: ALL-022 | B55: All files | C55: Delete | D55: Huỷ xoá (Keep it) | E55: App đã cài, đã qua first-run, đã cấp quyền bộ nhớ | F55: 1. ⋮ → Delete 2. Keep it | H55: File còn nguyên | I55: Đúng | J55: Pass | K55: Medium | L55: Functional
A56: ALL-023 | B56: All files | C56: Delete | D56: Xác nhận xoá | E56: App đã cài, đã qua first-run, đã cấp quyền bộ nhớ | F56: 1. ⋮ → Delete 2. Delete | G56: QA_renamed.pdf | H56: File bị xoá khỏi ổ đĩa và danh sách | I56: Đúng | J56: Pass | K56: High | L56: Functional
A57: ALL-024 | B57: All files | C57: Multi-select | D57: Nhấn giữ để vào chọn nhiều | E57: App đã cài, đã qua first-run, đã cấp quyền bộ nhớ | F57: 1. Long-press 1 dòng | H57: Mở MultiSelect, '1 selected', thanh Share/Merge/ZIP/Delete | I57: Đúng | J57: Pass | K57: High | L57: Functional
A58: ALL-025 | B58: All files | C58: Multi-select | D58: Select all / Clear | E58: Đang ở MultiSelect | F58: 1. Select all 2. Clear | H58: Đếm = tổng số file; Clear về 0 | I58: 135 → 0 | J58: Pass | K58: Medium | L58: Functional
A59: ALL-026 | B59: All files | C59: Multi-select | D59: Merge PDF từ chọn nhiều | E59: Chọn 2 PDF | F59: 1. Bấm Merge PDF | H59: Mở Merge step 2 với 2 file đã chọn | I59: Đúng | J59: Pass | K59: Medium | L59: Functional
A60: ALL-027 | B60: All files | C60: Multi-select | D60: ZIP / Share / Delete nhiều file | E60: Chọn ≥2 file | F60: 1. Thử ZIP, Share, Delete | H60: Hoạt động với toàn bộ file đã chọn | J60: Not run | K60: Medium | L60: Functional
A61: SRCH-001 | B61: Tìm kiếm | C61: Theo tên | D61: Tìm theo tên file | E61: App đã cài, đã qua first-run, đã cấp quyền bộ nhớ | F61: 1. Mở Search 2. Gõ 'Project' | G61: Project | H61: Mục 'In file names' liệt kê file khớp | I61: 3 kết quả | J61: Pass | K61: High | L61: Functional
A62: SRCH-002 | B62: Tìm kiếm | C62: Trong nội dung | D62: Tìm chữ trong nội dung PDF | E62: App đã cài, đã qua first-run, đã cấp quyền bộ nhớ | F62: 1. Gõ 'Tenant' | G62: Tenant | H62: Mục 'Inside your documents' có tên file, trang, đoạn trích | I62: Đúng, có snippet theo trang | J62: Pass | K62: High | L62: Functional
A63: SRCH-003 | B63: Tìm kiếm | C63: Chip | D63: Lọc chip Text / PDF | E63: Đã có kết quả | F63: 1. Bấm Text 2. Bấm PDF | H63: Text: No results (không có TXT chứa từ); PDF: lại có kết quả | I63: Đúng | J63: Pass | K63: Medium | L63: Functional
A64: SRCH-004 | B64: Tìm kiếm | C64: Không kết quả | D64: Từ khoá không tồn tại | E64: App đã cài, đã qua first-run, đã cấp quyền bộ nhớ | F64: 1. Gõ 'QA_xl' sau khi file bị mất khỏi MediaStore | H64: Empty state 'No results' | I64: Hiện No results | J64: Pass | K64: Low | L64: Negative
A65: SRCH-005 | B65: Tìm kiếm | C65: Clear | D65: Xoá ô tìm kiếm | E65: Đã gõ từ khoá | F65: 1. Bấm X | H65: Ô trống, hiện Recent searches | I65: Đúng | J65: Pass | K65: Medium | L65: Functional
A66: SRCH-006 | B66: Tìm kiếm | C66: Recent | D66: Lưu lịch sử khi bấm Search trên bàn phím / mở kết quả | E66: App đã cài, đã qua first-run, đã cấp quyền bộ nhớ | F66: 1. Gõ từ khoá 2. Bấm Search (IME) | H66: Từ khoá vào đầu Recent searches (tối đa 10, không trùng) | J66: Not run | K66: Low | L66: Functional
A67: SRCH-007 | B67: Tìm kiếm | C67: Recent | D67: Xoá 1 mục Recent | E67: Có recent search | F67: 1. Bấm X ở mục | H67: Mục bị xoá | J67: Not run | K67: Low | L67: Functional
A68: SRCH-008 | B68: Tìm kiếm | C68: Office | D68: File Office chỉ khớp theo tên | E68: App đã cài, đã qua first-run, đã cấp quyền bộ nhớ | F68: 1. Tìm 1 từ chỉ có trong nội dung DOCX | H68: Không có trong 'Inside your documents' (thiết kế) | J68: Not run | K68: Low | L68: Functional
A69: TOOL-001 | B69: Tab Tools | C69: Danh sách | D69: Hiển thị 17 công cụ theo nhóm | E69: App đã cài, đã qua first-run, đã cấp quyền bộ nhớ | F69: 1. Mở tab Tools | H69: '17 handy tools', nhóm Convert / Edit & Sign / Organize / Protect & more | I69: Đúng | J69: Pass | K69: Medium | L69: Functional
A70: TOOL-002 | B70: Tab Tools | C70: Danh sách | D70: Cuộn tới công cụ cuối (ZIP) ở chip All | E70: App đã cài, đã qua first-run, đã cấp quyền bộ nhớ | F70: 1. Tab Tools, chip All 2. Cuộn hết xuống | H70: Thấy và bấm được ô ZIP | I70: Ô ZIP bị thanh bottom bar che, không cuộn lên được | J70: Fail | K70: High | L70: UI | M70: BUG-05
A71: TOOL-003 | B71: Tab Tools | C71: Chip | D71: Lọc theo chip Protect | E71: App đã cài, đã qua first-run, đã cấp quyền bộ nhớ | F71: 1. Bấm chip Protect | H71: Chỉ còn Protect, Redact, OCR, Translate, ZIP | I71: Đúng | J71: Pass | K71: Medium | L71: Functional
A72: TOOL-004 | B72: Tab Tools | C72: Tile | D72: Tiêu đề/mô tả dài chạy chữ (marquee) | E72: App đã cài, đã qua first-run, đã cấp quyền bộ nhớ | F72: 1. Quan sát ô Photos to PDF, Office to PDF | H72: Chữ đọc được | I72: Mô tả chạy marquee, lúc chụp bị cắt dở (vd 'Pics in'), chấp nhận được | J72: Pass | K72: Low | L72: UI
A73: TOOL-005 | B73: Tab Tools | C73: Search tool | D73: Tìm công cụ | E73: App đã cài, đã qua first-run, đã cấp quyền bộ nhớ | F73: 1. Bấm kính lúp tab Tools 2. Gõ 'merge' | H73: Chỉ hiện Merge; từ không khớp hiện 'no tools' | J73: Not run | K73: Low | L73: Functional
A74: PICK-001 | B74: Chọn file (Step 1) | C74: Danh sách | D74: Hiển thị file PDF cho tool PDF | E74: App đã cài, đã qua first-run, đã cấp quyền bộ nhớ | F74: 1. Tools → Split | H74: Step 1 of 3, 'N PDFs on this phone', mới nhất ở đầu | I74: Đúng | J74: Pass | K74: Medium | L74: Functional
A75: PICK-002 | B75: Chọn file (Step 1) | C75: Search | D75: Tìm trong picker | E75: Đang ở picker | F75: 1. Gõ 'Rental' | G75: Rental | H75: Lọc còn file khớp | I75: 2 kết quả | J75: Pass | K75: Medium | L75: Functional
A76: PICK-003 | B76: Chọn file (Step 1) | C76: Search | D76: Không có kết quả | E76: Đang ở picker | F76: 1. Gõ 'zzzz' | G76: zzzz | H76: Empty state + nút Browse | I76: Đúng; dòng đếm ghi '0 PDFs on this phone' (nên là '0 kết quả') | J76: Pass | K76: Low | L76: UI
A77: PICK-004 | B77: Chọn file (Step 1) | C77: Multi pick | D77: Chọn nhiều file có đánh số (ZIP/Merge) | E77: Picker của ZIP | F77: 1. Chọn 2 file | H77: Số thứ tự 1,2 hiện trên file; thanh Next hiện | I77: Đúng | J77: Pass | K77: Medium | L77: Functional
A78: PICK-005 | B78: Chọn file (Step 1) | C78: File hỏng | D78: Chọn PDF hỏng cho Split | E78: Có QA_corrupt.pdf | F78: 1. Split → chọn QA_corrupt.pdf | G78: QA_corrupt.pdf | H78: Báo lỗi và ở lại picker để chọn file khác | I78: Toast 'Could not open this PDF' rồi đóng luôn cả picker, về tab Tools | J78: Fail | K78: Low | L78: Negative | M78: BUG-10
A79: PICK-006 | B79: Chọn file (Step 1) | C79: File có mật khẩu | D79: Chọn PDF có mật khẩu cho Watermark | E79: Có file protected | F79: 1. Watermark → chọn file protected | H79: Hỏi mật khẩu hoặc báo rõ file bị khoá | I79: Toast lỗi chung rồi về tab Tools | J79: Fail | K79: Low | L79: Negative | M79: BUG-10
A80: PICK-007 | B80: Chọn file (Step 1) | C80: Browse | D80: Browse folders | E80: Đang ở picker | F80: 1. Bấm Browse folders | H80: Mở trình chọn file hệ thống, chọn được file ngoài | J80: Not run | K80: Medium | L80: Functional
A81: MRG-001 | B81: Merge PDF | C81: Setup | D81: Màn sắp thứ tự | E81: Đã chọn 2 PDF | F81: 1. Mở Merge | H81: Step 2 of 3, tổng số trang, tên mặc định '<file1>-merged' | I81: Đúng | J81: Pass | K81: Medium | L81: Functional
A82: MRG-002 | B82: Merge PDF | C82: Setup | D82: Move up đổi thứ tự | E82: Màn Merge | F82: 1. Bấm Move up ở file 2 | H82: File 2 lên đầu, số thứ tự cập nhật | I82: Đúng | J82: Pass | K82: Medium | L82: Functional
A83: MRG-003 | B83: Merge PDF | C83: Setup | D83: Kéo thả đổi thứ tự | E83: Màn Merge | F83: 1. Kéo icon drag | H83: Thứ tự đổi theo | J83: Not run | K83: Low | L83: Functional
A84: MRG-004 | B84: Merge PDF | C84: Setup | D84: Add another file | E84: Màn Merge | F84: 1. Bấm Add another file | H84: Mở picker, thêm file vào cuối | J84: Not run | K84: Medium | L84: Functional
A85: MRG-005 | B85: Merge PDF | C85: Run | D85: Gộp 2 PDF | E85: Màn Merge | F85: 1. Merge 2 files | H85: Processing → Success, file mới có tổng số trang | I85: Success, 3.8 kB, mở thấy 2 trang | J85: Pass | K85: High | L85: Functional
A86: MRG-006 | B86: Merge PDF | C86: Run | D86: Gộp với 1 file | E86: Chỉ còn 1 file | F86: 1. Bấm Merge | H86: Nút bị chặn hoặc báo cần ≥2 file | J86: Not run | K86: Medium | L86: Negative
A87: SPL-001 | B87: Split PDF | C87: Setup | D87: Màn Split hiện 3 cách | E87: Chọn PDF 3 trang | F87: 1. Mở Split | H87: Every page / Custom ranges / Extract pages, ô ranges mặc định | I87: Đúng | J87: Pass | K87: Medium | L87: Functional
A88: SPL-002 | B88: Split PDF | C88: Validate | D88: Range vượt số trang | E88: Custom ranges | F88: 1. Nhập '5-9' | G88: 5-9 | H88: Báo lỗi, không chạy | I88: 'Check the pages: this PDF has 3', nút 'Split into 0 files' không chạy | J88: Pass | K88: Medium | L88: Negative
A89: SPL-003 | B89: Split PDF | C89: Validate | D89: Range chữ cái | E89: Custom ranges | F89: 1. Nhập 'abc' | G89: abc | H89: Báo lỗi | I89: Báo lỗi | J89: Pass | K89: Medium | L89: Negative
A90: SPL-004 | B90: Split PDF | C90: Validate | D90: Range ngược | E90: Custom ranges | F90: 1. Nhập '3-1' | G90: 3-1 | H90: Báo lỗi hoặc tự đảo | I90: Báo lỗi | J90: Pass | K90: Low | L90: Negative
A91: SPL-005 | B91: Split PDF | C91: Validate | D91: Nhãn nút khi range sai | E91: Range sai | F91: 1. Quan sát nút | H91: Nút disable với nhãn hợp lý | I91: Nút ghi 'Split into 0 files' – khó hiểu | J91: Fail | K91: Low | L91: UI | M91: BUG-12
A92: SPL-006 | B92: Split PDF | C92: Run | D92: Tách '1,3' thành 2 file | E92: Custom ranges | F92: 1. Nhập '1,3' 2. Split into 2 files | G92: 1,3 | H92: Success '2 files', tạo -1.pdf, -3.pdf | I92: Đúng | J92: Pass | K92: High | L92: Functional
A93: SPL-007 | B93: Split PDF | C93: Run | D93: Every page | E93: PDF nhiều trang | F93: 1. Chọn Every page → Split | H93: Mỗi trang 1 file | J93: Not run | K93: Medium | L93: Functional
A94: SPL-008 | B94: Split PDF | C94: Run | D94: Extract pages | E94: PDF nhiều trang | F94: 1. Extract pages → chọn trang | H94: 1 file chỉ gồm trang chọn | J94: Not run | K94: Medium | L94: Functional
A95: SPL-009 | B95: Split PDF | C95: Success | D95: Open khi kết quả nhiều file | E95: Success của Split | F95: 1. Bấm Open | H95: Mở file đầu tiên | I95: Mở '-1.pdf' | J95: Pass | K95: Low | L95: Functional
A96: CMP-001 | B96: Compress | C96: Setup | D96: Ước lượng dung lượng | E96: Chọn PDF | F96: 1. Mở Compress | H96: Right now / After about, 3 mức Light/Recommended/Strong | I96: Đúng | J96: Pass | K96: Medium | L96: Functional
A97: CMP-002 | B97: Compress | C97: Setup | D97: Change file | E97: Màn Compress | F97: 1. Bấm Change 2. Chọn file khác | H97: Màn cập nhật file mới | I97: Đúng | J97: Pass | K97: Medium | L97: Functional
A98: CMP-003 | B98: Compress | C98: Run | D98: Nén mức Strong file scan | E98: QA_scanned.pdf 62 kB | F98: 1. Strong → Make it smaller | H98: File nhỏ hơn, Success hiện % giảm | I98: 20 kB, 'Your PDF is 67% smaller' | J98: Pass | K98: High | L98: Functional
A99: CMP-004 | B99: Compress | C99: Run | D99: Nén file rất nhỏ / đã tối ưu | E99: PDF 2 kB | F99: 1. Make it smaller | H99: Báo không nhỏ hơn được hoặc vẫn tạo file hợp lệ | J99: Not run | K99: Low | L99: Edge
A100: PRT-001 | B100: Protect | C100: Validate | D100: Mật khẩu trống | E100: Màn Protect | F100: 1. Bấm Lock this file | H100: Không chạy | I100: Không chạy | J100: Pass | K100: Medium | L100: Negative
...

Sheet Bugs
A1: Bug ID | B1: Tiêu đề | C1: Mức độ | D1: Module | E1: Các bước tái hiện | F1: Kết quả thực tế | G1: Kết quả mong đợi | H1: Ghi chú / vị trí code | I1: Gợi ý sửa | J1: Ảnh chụp | K1: Trạng thái
A2: BUG-01 | B2: Restore draft xoá bản ghi MediaStore → file biến mất khỏi app | C2: High | D2: Office - Excel | E2: 1. Mở 1 file .xlsx, Edit, sửa 1 ô 2. Bấm Home rồi kill app (hoặc app bị hệ thống đóng) 3. Mở lại file → 'Welcome back!' → Restore my draft 4. Vào Search / All files tìm file đó | F2: Nội dung draft được ghi vào file (file trên ổ đĩa cập nhật), nhưng `content query` MediaStore trả 'No result found' và app không còn thấy file ở All files / Recent / Search / picker. | G2: File vẫn nằm trong danh sách với ngày sửa mới. | H2: Tái hiện 2 lần: Download/QA/Sales Report 2026.xlsx và Download/QA/QA_xl.xlsx. Lưu thường (Save → Save) không bị. | I2: Sau khi khôi phục draft (EditDrafts của SDK ghi đè bằng file tạm/rename), gọi MediaScannerConnection.scanFile(path) hoặc DocumentRepository.refresh() cho file đó. | J2: screenshots/BUG-01_RF8Y_xl_restored.png | K2: Open
A3: BUG-02 | B3: Fill form: Undo không bỏ tick checkbox | C3: Medium | D3: PDF Reader | E3: 1. Mở PDF có form (QA_form.pdf) 2. Fill form → chạm checkbox 'Agree' 3. Bấm Undo 4. Save, mở lại | F3: Checkbox vẫn tick, đếm 'n of 3 filled' không giảm; sau khi Save mở lại checkbox vẫn tick. | G3: Undo bỏ tick checkbox như với text field. | H3: QA_form.pdf được tạo kèm (samples/QA_form.pdf). | I3: Ghi thao tác toggle checkbox vào undo stack của FormMode/PDFView giống text field. | J3: screenshots/BUG-02_crop_RF8Y_fc2.png | K3: Open
A4: BUG-03 | B4: Excel: vừa bấm Edit đã báo 'Edited' và hỏi lưu khi thoát | C4: Medium | D4: Office - Excel | E4: 1. Mở Sales Report 2026.xlsx (store-assets/samples) 2. Bấm Edit, không sửa gì 3. Bấm X | F4: Trạng thái 'Edited', Undo sáng ngay khi vào Edit; thoát hiện 'Save before you go?'. File Excel trống (Untitled) thì không bị. | G4: Trạng thái 'Saved', thoát không hỏi. | H4: Tái hiện 2/2 lần. | I4: Kiểm tra lệnh SDK chạy khi startEditing với sheet có định dạng (chọn ô A1 / tính lại) đang làm bẩn undo stack; reset trạng thái 'dirty' sau khi vào Edit. | J4: screenshots/BUG-03_RF8Y_xl.png screenshots/BUG-03_RF8Y_x_close.png | K4: Open
A5: BUG-04 | B5: Watermark làm file phình to bất thường (2.4 kB → 1.4 MB) | C5: Medium | D5: Watermark | E5: 1. Tools → Watermark → chọn PDF 1 trang 2.4 kB 2. Text 'QA DRAFT', Flat, 50% → Stamp | F5: File kết quả 1.4 MB (gấp ~580 lần). | G5: Tăng vài kB (chỉ thêm 1 dòng chữ). | H5: QA_renamed (1)-watermark.pdf trong Download/Folio. | I5: Có thể đang nhúng nguyên font (hoặc ảnh raster) mỗi trang trong PdfToolbox watermark: dùng font chuẩn Helvetica/subset font, hoặc dùng chung 1 font object cho mọi trang. | J5: screenshots/BUG-04_RF8Y_wm_result.png | K5: Open
A6: BUG-05 | B6: Tab Tools (All): ô cuối (ZIP) bị thanh bottom bar che, không cuộn tới được | C6: Medium | D6: Tab Tools | E6: 1. Mở tab Tools, chip All 2. Cuộn xuống hết | F6: Hàng cuối (ZIP) nằm dưới thanh Files/Tools/Settings và nút +, không cuộn lên thêm được; chỉ chọn được ZIP khi lọc chip Protect. | G6: Toàn bộ ô cuối hiển thị phía trên thanh nổi. | H6: res/layout/fragment_tools.xml: NestedScrollView/layoutSections không có paddingBottom chừa chỗ cho bottom bar (FrameLayout chỉ có paddingBottom _12sdp). | I6: Thêm paddingBottom (~ chiều cao bottom bar + margin, khoảng _90sdp) cho layoutSections và clipToPadding=false cho NestedScrollView. | J6: screenshots/BUG-05_RF8Y_tools_bottom2.png screenshots/BUG-05_RF8Y_tools_protect.png | K6: Open
A7: BUG-06 | B7: Thiếu bản dịch: đổi sang Tiếng Việt nhiều chữ vẫn tiếng Anh | C7: Medium | D7: Settings / Đa ngôn ngữ | E7: 1. Settings → Language → Tiếng Việt → Continue 2. Xem tab Files, Tools | F7: 'Good evening', 'What’s on today?', 'N files on this phone', 'Start something new', 'Edit any document', 'Fill forms', 'Toolbox', '17 handy tools for your files' vẫn tiếng Anh. | G7: Toàn bộ giao diện tiếng Việt. | H7: So khớp values/strings.xml với các locale: values-vi thiếu 319/764 chuỗi; ~329 chuỗi thiếu ở hầu hết 44 locale khác (chủ yếu fo_*). | I7: Dịch các chuỗi fo_* còn thiếu cho 45 locale (hoặc chạy lint MissingTranslation để liệt kê). | J7: screenshots/BUG-06_RF8Y_vi_main.png screenshots/BUG-06_RF8Y_vi_tools.png | K7: Open
A8: BUG-07 | B8: Annotate: dòng gợi ý không đổi khi đổi công cụ | C8: Low | D8: PDF Reader | E8: 1. Mở PDF → Annotate 2. Chọn Pen, rồi Eraser, Select | F8: Dòng gợi ý vẫn 'Highlight · drag over the words'; chỉ cập nhật khi có render() khác (vd sau khi thêm Note). | G8: Gợi ý đúng công cụ đang chọn (Pen · …, Eraser · …). | H8: PdfReaderActivity.kt:646 applyAnnotateTool() không cập nhật tvAnnotateHint (chỉ set trong render(), dòng 1062). | I8: Gọi render() (hoặc cập nhật tvAnnotateHint) ở cuối applyAnnotateTool(). | J8: screenshots/BUG-07_RF8Y_annot2.png screenshots/BUG-07_RF8Y_erased.png | K8: Open
A9: BUG-08 | B9: ZIP: tên mặc định giữ tên file đã bị xoá khỏi danh sách | C9: Low | D9: ZIP | E9: 1. ZIP → chọn QA_scanned + QA_small → Next 2. Remove cả 2 3. Add more files → chọn Sales Report 2026.* | F9: Tên ZIP vẫn 'QA_scanned'. | G9: Tên mặc định theo file đầu hiện tại (nếu người dùng chưa tự sửa tên). | I9: Cập nhật edtName khi danh sách đổi và người dùng chưa sửa tên. | K9: Open
A10: BUG-09 | B10: Lưu file Office không cập nhật ngày sửa trong MediaStore → sắp xếp theo ngày sai | C10: Low | D10: Office / Data | E10: 1. Sửa và Save Product Launch.pptx 2. All files → Sort Date modified Newest first | F10: MediaStore vẫn giữ date_modified cũ (25/10 08:54) dù file trên ổ đĩa đã đổi lúc 00:49 ngày 26/10; file không lên đầu danh sách Recent/Newest. | G10: Ngày sửa cập nhật, file lên đầu. | H10: Kiểm tra bằng adb `content query` so với `ls -l`. | I10: Sau khi Save Office/PDF, quét lại file bằng MediaScannerConnection.scanFile. | K10: Open
A11: BUG-10 | B11: Chọn PDF hỏng / có mật khẩu trong tool: đóng luôn picker | C11: Low | D11: Chọn file | E11: 1. Tools → Split (hoặc Watermark) → chọn QA_corrupt.pdf hoặc file -protected | F11: Toast lỗi rồi màn setup và cả picker đều đóng, về tab Tools; phải chọn lại tool từ đầu. File có mật khẩu không được hỏi mật khẩu. | G11: Ở lại picker để chọn file khác; với file có mật khẩu thì hỏi mật khẩu. | H11: SplitActivity.kt:90-92 toast + finish(); WatermarkActivity.kt:75 tương tự. | I11: Quay lại picker thay vì finish cả luồng; dùng OpenPasswordDialog cho file khoá. | K11: Open
A12: BUG-11 | B12: Accessibility: nút tìm trong PDF reader đọc là 'Search files' | C12: Low | D12: Accessibility | E12: 1. Mở PDF, bật TalkBack, chạm nút kính lúp | F12: content-desc 'Search files'. | G12: 'Search in document'. | H12: activity_pdf_reader.xml btnSearch | I12: Đổi contentDescription. | K12: Open
A13: BUG-12 | B13: Split: range sai thì nút ghi 'Split into 0 files' | C13: Low | D13: Split | E13: 1. Split → Custom ranges → nhập '5-9' cho PDF 3 trang | F13: Nút ghi 'Split into 0 files'. | G13: Nút disable với nhãn bình thường, lỗi hiện ở dòng gợi ý (đã có). | K13: Open
A14: BUG-13 | B14: Excel/PPT: thanh tab ribbon nhảy vị trí khi đổi tab | C14: Low | D14: Office | E14: 1. Edit XLSX → bấm Home, Insert, Cells | F14: Tab Insert có nhãn dưới icon nên ribbon cao hơn, thanh tab bị đẩy lên; bấm theo vị trí cũ dễ trượt. | G14: Chiều cao ribbon cố định giữa các tab. | I14: Đặt chiều cao cố định cho rcvRibbon hoặc dùng cùng kiểu item cho mọi tab. | J14: screenshots/BUG-13_RF8Y_xl_sheet.png screenshots/BUG-13_RF8Y_xl_sheet2.png | K14: Open
A15: BUG-14 | B15: Fill form: 'Next field' ở trường cuối quay vòng về trường đầu | C15: Low | D15: PDF Reader | E15: 1. Fill form, tới 'Field 3 of 3' 2. Next field | F15: Nhảy về field 1 và mở dialog nhập. | G15: Nút đổi thành Done / báo đã hết trường. | J15: screenshots/BUG-14_RF8Y_form_f3.png | K15: Open
A16: BUG-15 | B16: Sign: Date và Initials đặt chồng lên nhau ở giữa màn | C16: Low | D16: PDF Reader | E16: 1. Sign → Date → Initials | F16: Cả 2 đặt cùng tâm màn hình, chồng nhau. | G16: Mục mới lệch xuống hoặc đặt tại chỗ chạm. | I16: Dịch vị trí mặc định của item mới nếu trùng item trước. | J16: screenshots/BUG-15_RF8Y_sign_saved.png | K16: Open

Sheet Crash & Stress
A1: Lần chạy | B1: Màn bắt đầu | C1: Lệnh | D1: Số sự kiện | E1: Crash | F1: ANR | G1: Kết quả
A2: M1 | B2: Launcher (toàn app) | C2: adb shell monkey -p com.af010.creator.docreader -s 2026 --throttle 120 --pct-appswitch 5 --pct-touch 55 --pct-motion 20 -v 6000 | D2: 6000 | E2: 0 | F2: 0 | G2: Pass
A3: M2 | B3: PDF reader (QA_form.pdf) | C3: monkey -s 101 --throttle 100 --pct-appswitch 0 --pct-touch 60 --pct-motion 25 -v 3000 | D3: 3000 | E3: 0 | F3: 0 | G3: Pass
A4: M3 | B4: Word (QA_word.docx) | C4: monkey -s 202 … -v 3000 | D4: 3000 | E4: 0 | F4: 0 | G4: Pass
A5: M4 | B5: Excel (QA_xl.xlsx) | C5: monkey -s 303 … -v 3000 | D5: 3000 | E5: 0 | F5: 0 | G5: Pass
A6: M5 | B6: PowerPoint (Product Launch.pptx) | C6: monkey -s 404 … -v 3000 | D6: 3000 | E6: 0 | F6: 0 | G6: Pass
A7: M6 | B7: Tab Tools | C7: monkey -s 505 … -v 4000 | D7: 4000 | E7: 0 | F7: 0 | G7: Pass
A8: Tổng | D8: =SUM(D2:D7) | E8: =SUM(E2:E7) | F8: =SUM(F2:F7)
A10: Crash và ANR lọc theo package com.af010.creator.docreader trong logcat -b crash và -b events (am_anr).
A11: Trước và sau khi chạy monkey đã chụp danh sách file trong /sdcard/Download và /sdcard/Documents: không file nào bị xoá hay sửa, chỉ có thêm Untitled-Oct-26-2.docx và .pptx do monkey bấm tạo file mới.
A12: Ngoài monkey: xoay màn hình khi đang sửa (app khoá dọc, không mất dữ liệu), kill tiến trình khi đang ở Contents của reader (khôi phục đúng màn), mở PDF hỏng / 0 byte / có mật khẩu: không crash.
A13: Một crash khác xuất hiện trong logcat lúc 23:59 (com.editor.scantoword.test, thiếu AndroidJUnitRunner) thuộc app khác trên máy, không phải Folio.
